{
  "name": "Heung Yuen Restaurant",
  "id": "heung-yuen-restaurant-san-francisco",
  "display_phone": "(415) 648-2666",
  "review_count": 201,
  "price": "$",
  "coordinates": {
    "longitude": -122.4203735,
    "latitude": 37.7552018
  },
  "location": {
    "address3": "",
    "address2": "",
    "address1": "3279 22nd St",
    "city": "San Francisco",
    "country": "US",
    "zip_code": "94110",
    "state": "CA",
    "display_address": [
      "3279 22nd St",
      "San Francisco, CA 94110"
    ]
  },
  "transactions": [],
  "rating": 4.0,
  "url": "https://www.yelp.com/biz/heung-yuen-restaurant-san-francisco?adjust_creative=0T9f6kHMnzQCXJKBQD97qw&utm_campaign=yelp_api_v3&utm_medium=api_v3_business_search&utm_source=0T9f6kHMnzQCXJKBQD97qw",
  "image_url": "https://s3-media3.fl.yelpcdn.com/bphoto/JjlI1ka6S75qETcxSHwbJA/o.jpg",
  "phone": "+14156482666",
  "is_closed": false,
  "categories": [
    {
      "alias": "chinese",
      "title": "Chinese"
    }
  ],
  "distance": 10.118198030216
}