{
  "categories": [
    {
      "alias": "coffee",
      "title": "Coffee & Tea"
    }
  ],
  "distance": 1298.4669465064,
  "display_phone": "(415) 391-5966",
  "is_closed": true,
  "transactions": [],
  "location": {
    "zip_code": "94111",
    "country": "US",
    "address2": "",
    "address3": "",
    "address1": "505 Sansome St",
    "state": "CA",
    "display_address": [
      "505 Sansome St",
      "San Francisco, CA 94111"
    ],
    "city": "San Francisco"
  },
  "id": "starbucks-san-francisco-124",
  "phone": "+14153915966",
  "rating": 4.0,
  "image_url": "https://s3-media2.fl.yelpcdn.com/bphoto/-3YUb4Xr4tDFk71byYe_TQ/o.jpg",
  "url": "https://www.yelp.com/biz/starbucks-san-francisco-124?adjust_creative=0T9f6kHMnzQCXJKBQD97qw&utm_campaign=yelp_api_v3&utm_medium=api_v3_business_search&utm_source=0T9f6kHMnzQCXJKBQD97qw",
  "coordinates": {
    "longitude": -122.401824951172,
    "latitude": 37.7950706481934
  },
  "review_count": 58,
  "price": "$",
  "name": "Starbucks"
}