{
  "name": "The Golden Donut",
  "id": "the-golden-donut-san-francisco",
  "display_phone": "(415) 422-0623",
  "review_count": 85,
  "price": "$",
  "coordinates": {
    "longitude": -122.477409169078,
    "latitude": 37.7803348749876
  },
  "location": {
    "address3": "",
    "address2": "",
    "address1": "5401 Geary Blvd",
    "city": "San Francisco",
    "country": "US",
    "zip_code": "94121",
    "state": "CA",
    "display_address": [
      "5401 Geary Blvd",
      "San Francisco, CA 94121"
    ]
  },
  "transactions": [],
  "rating": 4.0,
  "url": "https://www.yelp.com/biz/the-golden-donut-san-francisco?adjust_creative=0T9f6kHMnzQCXJKBQD97qw&utm_campaign=yelp_api_v3&utm_medium=api_v3_business_search&utm_source=0T9f6kHMnzQCXJKBQD97qw",
  "image_url": "https://s3-media3.fl.yelpcdn.com/bphoto/dlsBUH6eRxnWxHhQylvmnw/o.jpg",
  "phone": "+14154220623",
  "is_closed": false,
  "categories": [
    {
      "alias": "donuts",
      "title": "Donuts"
    },
    {
      "alias": "coffee",
      "title": "Coffee & Tea"
    },
    {
      "alias": "sandwiches",
      "title": "Sandwiches"
    }
  ],
  "distance": 14.10614834384
}