{
  "name": "California Pacific Medical Center",
  "id": "california-pacific-medical-center-san-francisco-3",
  "display_phone": "(415) 600-6000",
  "review_count": 232,
  "coordinates": {
    "longitude": -122.4560662,
    "latitude": 37.7862031
  },
  "location": {
    "address3": "",
    "address2": "",
    "address1": "3700 California St",
    "city": "San Francisco",
    "country": "US",
    "zip_code": "94118",
    "state": "CA",
    "display_address": [
      "3700 California St",
      "San Francisco, CA 94118"
    ]
  },
  "transactions": [],
  "rating": 4.0,
  "url": "https://www.yelp.com/biz/california-pacific-medical-center-san-francisco-3?adjust_creative=0T9f6kHMnzQCXJKBQD97qw&utm_campaign=yelp_api_v3&utm_medium=api_v3_business_search&utm_source=0T9f6kHMnzQCXJKBQD97qw",
  "image_url": "https://s3-media4.fl.yelpcdn.com/bphoto/q_Tju_NY5ghAqAxLK3nN1w/o.jpg",
  "phone": "+14156006000",
  "is_closed": false,
  "categories": [
    {
      "alias": "medcenters",
      "title": "Medical Centers"
    },
    {
      "alias": "hospitals",
      "title": "Hospitals"
    }
  ],
  "distance": 2647.705801948
}