{
  "name": "Legion of Honor",
  "id": "legion-of-honor-san-francisco",
  "display_phone": "(415) 750-3600",
  "review_count": 711,
  "coordinates": {
    "longitude": -122.500802,
    "latitude": 37.784927
  },
  "location": {
    "address3": "",
    "address2": "100 34th Avenue",
    "address1": "Lincoln Park",
    "city": "San Francisco",
    "country": "US",
    "zip_code": "94121",
    "state": "CA",
    "display_address": [
      "Lincoln Park",
      "100 34th Avenue",
      "San Francisco, CA 94121"
    ]
  },
  "transactions": [],
  "rating": 4.5,
  "url": "https://www.yelp.com/biz/legion-of-honor-san-francisco?adjust_creative=0T9f6kHMnzQCXJKBQD97qw&utm_campaign=yelp_api_v3&utm_medium=api_v3_business_search&utm_source=0T9f6kHMnzQCXJKBQD97qw",
  "image_url": "https://s3-media2.fl.yelpcdn.com/bphoto/KxnDORvTdQD7O1B1aNdGYA/o.jpg",
  "phone": "+14157503600",
  "is_closed": false,
  "categories": [
    {
      "alias": "museums",
      "title": "Museums"
    }
  ],
  "distance": 103.96667119370001
}