{
  "name": "Bob's Donut & Pastry Shop",
  "id": "bobs-donut-and-pastry-shop-san-francisco-2",
  "display_phone": "(415) 776-3141",
  "review_count": 2332,
  "price": "$",
  "coordinates": {
    "longitude": -122.42128,
    "latitude": 37.7918499
  },
  "location": {
    "address3": "",
    "address2": "",
    "address1": "1621 Polk St",
    "city": "San Francisco",
    "country": "US",
    "zip_code": "94109",
    "state": "CA",
    "display_address": [
      "1621 Polk St",
      "San Francisco, CA 94109"
    ]
  },
  "transactions": [],
  "rating": 4.5,
  "url": "https://www.yelp.com/biz/bobs-donut-and-pastry-shop-san-francisco-2?adjust_creative=0T9f6kHMnzQCXJKBQD97qw&utm_campaign=yelp_api_v3&utm_medium=api_v3_business_search&utm_source=0T9f6kHMnzQCXJKBQD97qw",
  "image_url": "https://s3-media4.fl.yelpcdn.com/bphoto/5aGWvn2V4kOwbUTv2-81XQ/o.jpg",
  "phone": "+14157763141",
  "is_closed": false,
  "categories": [
    {
      "alias": "bakeries",
      "title": "Bakeries"
    },
    {
      "alias": "donuts",
      "title": "Donuts"
    }
  ],
  "distance": 21.39668707012
}