{
  "categories": [
    {
      "alias": "grocery",
      "title": "Grocery"
    }
  ],
  "distance": 13.59012956624,
  "display_phone": "(415) 982-6137",
  "is_closed": false,
  "transactions": [],
  "location": {
    "zip_code": "94108",
    "country": "US",
    "address2": "",
    "address3": "",
    "address1": "863 Washington St",
    "state": "CA",
    "display_address": [
      "863 Washington St",
      "San Francisco, CA 94108"
    ],
    "city": "San Francisco"
  },
  "id": "wo-chong-company-san-francisco-3",
  "phone": "+14159826137",
  "rating": 4.5,
  "image_url": "https://s3-media2.fl.yelpcdn.com/bphoto/fXRYZa_pGo3EU1ykpS9Upw/o.jpg",
  "url": "https://www.yelp.com/biz/wo-chong-company-san-francisco-3?adjust_creative=0T9f6kHMnzQCXJKBQD97qw&utm_campaign=yelp_api_v3&utm_medium=api_v3_business_search&utm_source=0T9f6kHMnzQCXJKBQD97qw",
  "coordinates": {
    "longitude": -122.4075928,
    "latitude": 37.794899
  },
  "review_count": 7,
  "price": "$",
  "name": "Wo Chong Company"
}