{
  "name": "Cafe 24",
  "id": "cafe-24-san-francisco",
  "display_phone": "(415) 514-4114",
  "review_count": 42,
  "price": "$$",
  "coordinates": {
    "longitude": -122.391373962164,
    "latitude": 37.7668426930904
  },
  "location": {
    "address3": "",
    "address2": null,
    "address1": "600 16th St",
    "city": "San Francisco",
    "country": "US",
    "zip_code": "94158",
    "state": "CA",
    "display_address": [
      "600 16th St",
      "San Francisco, CA 94158"
    ]
  },
  "transactions": [],
  "rating": 3.5,
  "url": "https://www.yelp.com/biz/cafe-24-san-francisco?adjust_creative=0T9f6kHMnzQCXJKBQD97qw&utm_campaign=yelp_api_v3&utm_medium=api_v3_business_search&utm_source=0T9f6kHMnzQCXJKBQD97qw",
  "image_url": "https://s3-media4.fl.yelpcdn.com/bphoto/uCT8WhddcwwhNduGjhD5FA/o.jpg",
  "phone": "+14155144114",
  "is_closed": false,
  "categories": [
    {
      "alias": "delis",
      "title": "Delis"
    }
  ],
  "distance": 557.148116711
}