{
  "name": "Alex Gourmet Burrito",
  "id": "alex-gourmet-burrito-san-francisco",
  "display_phone": "(415) 362-1384",
  "review_count": 117,
  "price": "$",
  "coordinates": {
    "longitude": -122.401870727539,
    "latitude": 37.7954597473145
  },
  "location": {
    "address3": "",
    "address2": null,
    "address1": "545 Sansome St",
    "city": "San Francisco",
    "country": "US",
    "zip_code": "94111",
    "state": "CA",
    "display_address": [
      "545 Sansome St",
      "San Francisco, CA 94111"
    ]
  },
  "transactions": [],
  "rating": 3.0,
  "url": "https://www.yelp.com/biz/alex-gourmet-burrito-san-francisco?adjust_creative=0T9f6kHMnzQCXJKBQD97qw&utm_campaign=yelp_api_v3&utm_medium=api_v3_business_search&utm_source=0T9f6kHMnzQCXJKBQD97qw",
  "image_url": "https://s3-media4.fl.yelpcdn.com/bphoto/dRHcyRfYsAPeRedCe2XRYQ/o.jpg",
  "phone": "+14153621384",
  "is_closed": false,
  "categories": [
    {
      "alias": "mexican",
      "title": "Mexican"
    }
  ],
  "distance": 4895.400973658
}