{
  "name": "Chang's Kitchen",
  "id": "changs-kitchen-san-francisco",
  "display_phone": "(415) 731-8110",
  "review_count": 280,
  "price": "$$",
  "coordinates": {
    "longitude": -122.46905,
    "latitude": 37.76417
  },
  "location": {
    "address3": null,
    "address2": null,
    "address1": "1030 Irving St",
    "city": "San Francisco",
    "country": "US",
    "zip_code": "94122",
    "state": "CA",
    "display_address": [
      "1030 Irving St",
      "San Francisco, CA 94122"
    ]
  },
  "transactions": [
    "delivery",
    "pickup"
  ],
  "rating": 4.0,
  "url": "https://www.yelp.com/biz/changs-kitchen-san-francisco?adjust_creative=0T9f6kHMnzQCXJKBQD97qw&utm_campaign=yelp_api_v3&utm_medium=api_v3_business_search&utm_source=0T9f6kHMnzQCXJKBQD97qw",
  "image_url": "https://s3-media3.fl.yelpcdn.com/bphoto/HMIOyos1vUQIh5z1-ecxKA/o.jpg",
  "phone": "+14157318110",
  "is_closed": false,
  "categories": [
    {
      "alias": "chinese",
      "title": "Chinese"
    }
  ],
  "distance": 2891.5742420359998
}