{
  "name": "Boba Delight",
  "id": "boba-delight-san-francisco-6",
  "display_phone": "(415) 374-7933",
  "review_count": 89,
  "price": "$",
  "coordinates": {
    "longitude": -122.417294669975,
    "latitude": 37.7827825617467
  },
  "location": {
    "address3": "",
    "address2": "",
    "address1": "528 Larkin",
    "city": "San Francisco",
    "country": "US",
    "zip_code": "94102",
    "state": "CA",
    "display_address": [
      "528 Larkin",
      "San Francisco, CA 94102"
    ]
  },
  "transactions": [],
  "rating": 3.5,
  "url": "https://www.yelp.com/biz/boba-delight-san-francisco-6?adjust_creative=0T9f6kHMnzQCXJKBQD97qw&utm_campaign=yelp_api_v3&utm_medium=api_v3_business_search&utm_source=0T9f6kHMnzQCXJKBQD97qw",
  "image_url": "https://s3-media4.fl.yelpcdn.com/bphoto/XtLJo8yCxBVyMoWgrPfa1Q/o.jpg",
  "phone": "+14153747933",
  "is_closed": false,
  "categories": [
    {
      "alias": "bubbletea",
      "title": "Bubble Tea"
    },
    {
      "alias": "coffee",
      "title": "Coffee & Tea"
    },
    {
      "alias": "gelato",
      "title": "Gelato"
    }
  ],
  "distance": 2958.86895507
}