{
  "name": "Hot Dog on a Stick",
  "id": "hot-dog-on-a-stick-san-francisco",
  "display_phone": "(415) 665-9609",
  "review_count": 70,
  "price": "$",
  "coordinates": {
    "longitude": -122.47688,
    "latitude": 37.72856
  },
  "location": {
    "address3": "",
    "address2": "",
    "address1": "3251 20th Ave",
    "city": "San Francisco",
    "country": "US",
    "zip_code": "94132",
    "state": "CA",
    "display_address": [
      "3251 20th Ave",
      "San Francisco, CA 94132"
    ]
  },
  "transactions": [],
  "rating": 4.0,
  "url": "https://www.yelp.com/biz/hot-dog-on-a-stick-san-francisco?adjust_creative=0T9f6kHMnzQCXJKBQD97qw&utm_campaign=yelp_api_v3&utm_medium=api_v3_business_search&utm_source=0T9f6kHMnzQCXJKBQD97qw",
  "image_url": "https://s3-media2.fl.yelpcdn.com/bphoto/0OFcfrj695GqObbgajdwsA/o.jpg",
  "phone": "+14156659609",
  "is_closed": false,
  "categories": [
    {
      "alias": "hotdog",
      "title": "Hot Dogs"
    },
    {
      "alias": "hotdogs",
      "title": "Fast Food"
    }
  ],
  "distance": 5123.722223741999
}