{
  "name": "Ike'spress Sandwiches",
  "id": "ikespress-sandwiches-san-francisco",
  "display_phone": "(415) 335-4369",
  "review_count": 68,
  "price": "$$",
  "coordinates": {
    "longitude": -122.407891033336,
    "latitude": 37.7852638812651
  },
  "location": {
    "address3": null,
    "address2": "",
    "address1": "63 Powell St",
    "city": "San Francisco",
    "country": "US",
    "zip_code": "94102",
    "state": "CA",
    "display_address": [
      "63 Powell St",
      "San Francisco, CA 94102"
    ]
  },
  "transactions": [
    "pickup"
  ],
  "rating": 2.0,
  "url": "https://www.yelp.com/biz/ikespress-sandwiches-san-francisco?adjust_creative=0T9f6kHMnzQCXJKBQD97qw&utm_campaign=yelp_api_v3&utm_medium=api_v3_business_search&utm_source=0T9f6kHMnzQCXJKBQD97qw",
  "image_url": "https://s3-media2.fl.yelpcdn.com/bphoto/FfxsZj4oE4p0U88MMQBF8w/o.jpg",
  "phone": "+14153354369",
  "is_closed": false,
  "categories": [
    {
      "alias": "sandwiches",
      "title": "Sandwiches"
    },
    {
      "alias": "popuprestaurants",
      "title": "Pop-Up Restaurants"
    }
  ],
  "distance": 3693.1858522999996
}